test_pioneer/__init__.py
test_pioneer/__main__.py
test_pioneer/executor/__init__.py
test_pioneer/executor/pioneer_executor.py
test_pioneer/executor/browser/__init__.py
test_pioneer/executor/browser/url.py
test_pioneer/executor/file/__init__.py
test_pioneer/executor/file/file_processing.py
test_pioneer/executor/program/__init__.py
test_pioneer/executor/program/external_program.py
test_pioneer/executor/run/__init__.py
test_pioneer/executor/run/executor_run.py
test_pioneer/executor/run/executor_run_folder.py
test_pioneer/executor/run/parallel_run.py
test_pioneer/executor/run/process_manager.py
test_pioneer/executor/run/utils.py
test_pioneer/executor/test_recorder/__init__.py
test_pioneer/executor/test_recorder/logger.py
test_pioneer/executor/test_recorder/video_recoder.py
test_pioneer/executor/time/__init__.py
test_pioneer/executor/time/wait.py
test_pioneer/logging/__init__.py
test_pioneer/logging/loggin_instance.py
test_pioneer/process/__init__.py
test_pioneer/process/execute_process.py
test_pioneer/process/process_manager.py
test_pioneer/project/__init__.py
test_pioneer/project/create_template_structure.py
test_pioneer/project/template/__init__.py
test_pioneer/project/template/template.py
test_pioneer/utils/__init__.py
test_pioneer/utils/exception/__init__.py
test_pioneer/utils/exception/exceptions.py
test_pioneer/utils/exception/tags.py
test_pioneer/utils/package/__init__.py
test_pioneer/utils/package/check.py
test_pioneer_dev-0.1.36.dist-info/licenses/LICENSE
test_pioneer_dev-0.1.36.dist-info/METADATA
test_pioneer_dev-0.1.36.dist-info/WHEEL
test_pioneer_dev-0.1.36.dist-info/top_level.txt
test_pioneer_dev-0.1.36.dist-info/RECORD
